bettermap/__init__.py
bettermap/bettermap.py
bettermap-1.3.1.dist-info/LICENSE
bettermap-1.3.1.dist-info/METADATA
bettermap-1.3.1.dist-info/WHEEL
bettermap-1.3.1.dist-info/top_level.txt
bettermap-1.3.1.dist-info/RECORD
