Metadata-Version: 2.1
Name: bettermap
Version: 1.3.1
Summary: Parallelized drop-in replacements for Python's map function
Home-page: https://github.com/allenai/bettermap
Author: Dirk Groeneveld
Author-email: dirkg@allenai.org
License: Apache
Platform: UNKNOWN
Requires-Python: >=3.6
License-File: LICENSE
Requires-Dist: dill
Provides-Extra: dev
Requires-Dist: flaky ; extra == 'dev'
Requires-Dist: mypy ; extra == 'dev'
Requires-Dist: packaging ; extra == 'dev'
Requires-Dist: pytest-sphinx ; extra == 'dev'
Requires-Dist: pytest (>=6.2.5) ; extra == 'dev'
Requires-Dist: setuptools ; extra == 'dev'
Requires-Dist: twine (>=1.11.0) ; extra == 'dev'
Requires-Dist: wheel ; extra == 'dev'
